visionapi/__init__.py
visionapi/app.py
visionapi/utils.py
VisionAPI-0.1.4.dist-info/LICENSE
VisionAPI-0.1.4.dist-info/METADATA
VisionAPI-0.1.4.dist-info/WHEEL
VisionAPI-0.1.4.dist-info/top_level.txt
VisionAPI-0.1.4.dist-info/RECORD
