Metadata-Version: 2.1
Name: VisionAPI
Version: 0.1.4
Summary: VisionAPI - a Python library for GPT-Based Vision Models inference
Home-page: https://github.com/josebenitezg/VisionAPI
Author: Jose Benitez
Author-email: benitez.ing@gmial.com
License: MIT
Classifier: Development Status :: 3 - Alpha
Classifier: Intended Audience :: Developers
Classifier: License :: OSI Approved :: MIT License
Classifier: Programming Language :: Python :: 3
Classifier: Programming Language :: Python :: 3.8
Classifier: Programming Language :: Python :: 3.9
Classifier: Programming Language :: Python :: 3.10
Classifier: Programming Language :: Python :: 3.11
Classifier: Programming Language :: Python :: 3 :: Only
Classifier: Topic :: Software Development :: Libraries :: Python Modules
Requires-Python: >=3.8,<3.12.0
License-File: LICENSE
Requires-Dist: openai
Requires-Dist: opencv-python
Requires-Dist: numpy
Requires-Dist: gradio ==3.50.2
